openrouter_model_filter/__init__.py
openrouter_model_filter/__main__.py
openrouter_model_filter/filter.py
openrouter_model_filter-1.0.0.dist-info/licenses/LICENSE
openrouter_model_filter-1.0.0.dist-info/METADATA
openrouter_model_filter-1.0.0.dist-info/WHEEL
openrouter_model_filter-1.0.0.dist-info/entry_points.txt
openrouter_model_filter-1.0.0.dist-info/top_level.txt
openrouter_model_filter-1.0.0.dist-info/RECORD
